aio_databases/__init__.py
aio_databases/backends/__init__.py
aio_databases/backends/_aiomysql.py
aio_databases/backends/_aioodbc.py
aio_databases/backends/_aiopg.py
aio_databases/backends/_aiosqlite.py
aio_databases/backends/_asyncpg.py
aio_databases/backends/_dummy.py
aio_databases/backends/_trio_mysql.py
aio_databases/backends/_triopg.py
aio_databases/backends/common.py
aio_databases/database.py
aio_databases/log.py
aio_databases/py.typed
aio_databases/record.py
aio_databases/types.py
aio_databases-1.1.0.dist-info/METADATA
aio_databases-1.1.0.dist-info/WHEEL
aio_databases-1.1.0.dist-info/RECORD
