Metadata-Version: 2.1
Name: aio-databases
Version: 1.1.0
Summary: Async support for various databases
Home-page: https://github.com/klen/aio-databases
License: MIT
Keywords: asyncio,trio,databases,mysql,sqlite,postgres,postgresql
Author: Kirill Klenov
Author-email: horneds@gmail.com
Requires-Python: >=3.9,<4.0
Classifier: Development Status :: 5 - Production/Stable
Classifier: Framework :: AsyncIO
Classifier: Framework :: Trio
Classifier: Intended Audience :: Developers
Classifier: License :: OSI Approved :: MIT License
Classifier: Programming Language :: Python
Classifier: Programming Language :: Python :: 3
Classifier: Programming Language :: Python :: 3.9
Classifier: Programming Language :: Python :: 3.10
Classifier: Programming Language :: Python :: 3.11
Classifier: Programming Language :: Python :: 3.12
Classifier: Programming Language :: Python :: 3.13
Provides-Extra: aiomysql
Provides-Extra: aioodbc
Provides-Extra: aiopg
Provides-Extra: aiosqlite
Provides-Extra: asyncpg
Provides-Extra: trio-mysql
Provides-Extra: triopg
Requires-Dist: aiomysql ; extra == "aiomysql"
Requires-Dist: aioodbc ; extra == "aioodbc"
Requires-Dist: aiopg ; extra == "aiopg"
Requires-Dist: aiosqlite ; extra == "aiosqlite"
Requires-Dist: asyncpg ; extra == "asyncpg"
Requires-Dist: trio_mysql ; extra == "trio-mysql"
Requires-Dist: triopg ; extra == "triopg"
Project-URL: Repository, https://github.com/klen/aio-databases
